{"cameraMode":{"drawMode":0,"name":"Shaded","section":"Shading Mode"},"sceneLighting":true,"audioPlay":false,"sceneViewState":{"showFog":true,"showMaterialUpdate":false,"showSkybox":true,"showFlares":true,"showImageEffects":true,"showParticleSystems":true},"in2DMode":false,"pivot":{"x":-2.8891477584838869,"y":0.5783507823944092,"z":3.353210926055908},"rotation":{"x":0.1496477723121643,"y":0.03558231145143509,"z":-0.005388898774981499,"w":0.9880842566490173},"size":7.284445285797119,"orthographic":false}